{
  "/_not-found/page": "app/_not-found/page.js",
  "/admin/page": "app/admin/page.js",
  "/blog/[slug]/page": "app/blog/[slug]/page.js",
  "/auth/callback/route": "app/auth/callback/route.js",
  "/colaborador/page": "app/colaborador/page.js",
  "/content-admin/page": "app/content-admin/page.js",
  "/journal/page": "app/journal/page.js",
  "/editor/page": "app/editor/page.js",
  "/admin/books/[id]/edit/page": "app/admin/books/[id]/edit/page.js",
  "/blog/page": "app/blog/page.js",
  "/admin/books/new/page": "app/admin/books/new/page.js",
  "/login/forgot-password/page": "app/login/forgot-password/page.js",
  "/libro/[id]/page": "app/libro/[id]/page.js",
  "/login/page": "app/login/page.js",
  "/page": "app/page.js",
  "/admin/catalog/page": "app/admin/catalog/page.js",
  "/login/reset-password/page": "app/login/reset-password/page.js",
  "/login/register/page": "app/login/register/page.js"
}